salinic/__init__.py
salinic/backends/__init__.py
salinic/backends/solr/__init__.py
salinic/backends/solr/client.py
salinic/backends/solr/index.py
salinic/backends/solr/schema_manager.py
salinic/backends/solr/types.py
salinic/engine.py
salinic/field.py
salinic/index.py
salinic/query.py
salinic/schema.py
salinic/schema_manager.py
salinic/search.py
salinic/types.py
salinic/url.py
salinic/utils.py
salinic-0.6.1.dist-info/LICENSE
salinic-0.6.1.dist-info/METADATA
salinic-0.6.1.dist-info/WHEEL
salinic-0.6.1.dist-info/RECORD
