Metadata-Version: 2.1
Name: salinic
Version: 0.6.1
Summary: Search abstraction layer
Author: Eugen Ciur
Author-email: eugen@papermerge.com
Requires-Python: >=3.13,<4.0
Classifier: Programming Language :: Python :: 3
Classifier: Programming Language :: Python :: 3.13
Provides-Extra: xapian
Requires-Dist: glom (>=24.11,<25.0)
Requires-Dist: pydantic (>=2.10,<3.0)
Requires-Dist: requests (>=2.31.0,<3.0.0)
Requires-Dist: xapianpy (==1.4.22.post2406040406) ; extra == "xapian"
